omniart_eye_dataset/OmniArtEyeDataset.py
omniart_eye_dataset/__init__.py
omniart_eye_dataset-0.1.1.dist-info/METADATA
omniart_eye_dataset-0.1.1.dist-info/WHEEL
omniart_eye_dataset-0.1.1.dist-info/top_level.txt
omniart_eye_dataset-0.1.1.dist-info/RECORD
