Metadata-Version: 2.1
Name: omniart-eye-dataset
Version: 0.1.1
Summary: A PyTorch dataset of the eyes found in the OmniArt dataset
Home-page: http://github.com/rogierknoester/omniart_eye_dataset
Author: Rogier Knoester
Author-email: knoesterrogier+omniart@gmail.com
License: MIT
Platform: UNKNOWN
